odoo8_addon_web_ir_actions_act_window_message-8.0.1.0.0.99.dev19-py2.7-nspkg.pth
odoo8_addon_web_ir_actions_act_window_message-8.0.1.0.0.99.dev19.dist-info/DESCRIPTION.rst
odoo8_addon_web_ir_actions_act_window_message-8.0.1.0.0.99.dev19.dist-info/METADATA
odoo8_addon_web_ir_actions_act_window_message-8.0.1.0.0.99.dev19.dist-info/RECORD
odoo8_addon_web_ir_actions_act_window_message-8.0.1.0.0.99.dev19.dist-info/WHEEL
odoo8_addon_web_ir_actions_act_window_message-8.0.1.0.0.99.dev19.dist-info/metadata.json
odoo8_addon_web_ir_actions_act_window_message-8.0.1.0.0.99.dev19.dist-info/namespace_packages.txt
odoo8_addon_web_ir_actions_act_window_message-8.0.1.0.0.99.dev19.dist-info/top_level.txt
odoo_addons/web_ir_actions_act_window_message/README.rst
odoo_addons/web_ir_actions_act_window_message/__init__.py
odoo_addons/web_ir_actions_act_window_message/__openerp__.py
odoo_addons/web_ir_actions_act_window_message/i18n/ar.po
odoo_addons/web_ir_actions_act_window_message/i18n/bs.po
odoo_addons/web_ir_actions_act_window_message/i18n/ca.po
odoo_addons/web_ir_actions_act_window_message/i18n/cs.po
odoo_addons/web_ir_actions_act_window_message/i18n/de.po
odoo_addons/web_ir_actions_act_window_message/i18n/en_GB.po
odoo_addons/web_ir_actions_act_window_message/i18n/es.po
odoo_addons/web_ir_actions_act_window_message/i18n/es_CR.po
odoo_addons/web_ir_actions_act_window_message/i18n/es_EC.po
odoo_addons/web_ir_actions_act_window_message/i18n/es_ES.po
odoo_addons/web_ir_actions_act_window_message/i18n/es_MX.po
odoo_addons/web_ir_actions_act_window_message/i18n/es_VE.po
odoo_addons/web_ir_actions_act_window_message/i18n/et.po
odoo_addons/web_ir_actions_act_window_message/i18n/eu.po
odoo_addons/web_ir_actions_act_window_message/i18n/fi.po
odoo_addons/web_ir_actions_act_window_message/i18n/fr.po
odoo_addons/web_ir_actions_act_window_message/i18n/fr_CH.po
odoo_addons/web_ir_actions_act_window_message/i18n/hr.po
odoo_addons/web_ir_actions_act_window_message/i18n/hu.po
odoo_addons/web_ir_actions_act_window_message/i18n/it.po
odoo_addons/web_ir_actions_act_window_message/i18n/ja.po
odoo_addons/web_ir_actions_act_window_message/i18n/lt.po
odoo_addons/web_ir_actions_act_window_message/i18n/mk.po
odoo_addons/web_ir_actions_act_window_message/i18n/nb.po
odoo_addons/web_ir_actions_act_window_message/i18n/nl.po
odoo_addons/web_ir_actions_act_window_message/i18n/nl_BE.po
odoo_addons/web_ir_actions_act_window_message/i18n/pl.po
odoo_addons/web_ir_actions_act_window_message/i18n/pt.po
odoo_addons/web_ir_actions_act_window_message/i18n/pt_BR.po
